percolationAnalysis/__init__.py
percolationAnalysis/percolationAnalysis.py
percolationAnalysis/testData.bin
percolationAnalysis-1.0.0.2.dist-info/LICENSE
percolationAnalysis-1.0.0.2.dist-info/METADATA
percolationAnalysis-1.0.0.2.dist-info/WHEEL
percolationAnalysis-1.0.0.2.dist-info/top_level.txt
percolationAnalysis-1.0.0.2.dist-info/RECORD
